git_like-0.0.6.data/scripts/git-like
gitlike/__init__.py
gitlike/config.py
gitlike/git_wrapper.py
gitlike/gitlike_service.py
gitlike/like.py
gitlike/shared.py
git_like-0.0.6.dist-info/LICENSE.md
git_like-0.0.6.dist-info/METADATA
git_like-0.0.6.dist-info/WHEEL
git_like-0.0.6.dist-info/top_level.txt
git_like-0.0.6.dist-info/RECORD
