Metadata-Version: 2.1
Name: git-like
Version: 0.0.6
Summary: A small cli to like and receive likes four your code in a git controlled code base.
Home-page: https://github.com/ChillkroeteTTS/git-like-cli
Author: Tjark Smalla
Author-email: tjark.smalla@git-like.com
License: UNKNOWN
Platform: UNKNOWN
Classifier: Programming Language :: Python :: 3
Classifier: License :: OSI Approved :: MIT License
Classifier: Operating System :: OS Independent
Requires-Python: >=3.6
Requires-Dist: click
Requires-Dist: requests
Requires-Dist: boto3
Requires-Dist: gitpython
Requires-Dist: service
